taurus_pyqtgraph/__init__.py
taurus_pyqtgraph/archivingtool.py
taurus_pyqtgraph/autopantool.py
taurus_pyqtgraph/buffersizetool.py
taurus_pyqtgraph/cli.py
taurus_pyqtgraph/curveproperties.py
taurus_pyqtgraph/curvesmodel.py
taurus_pyqtgraph/curvespropertiestool.py
taurus_pyqtgraph/datainspectortool.py
taurus_pyqtgraph/dateaxisitem.py
taurus_pyqtgraph/exporters.py
taurus_pyqtgraph/forcedreadtool.py
taurus_pyqtgraph/legendtool.py
taurus_pyqtgraph/plot.py
taurus_pyqtgraph/statisticstool.py
taurus_pyqtgraph/taurusimageitem.py
taurus_pyqtgraph/taurusmodelchoosertool.py
taurus_pyqtgraph/taurusplotdataitem.py
taurus_pyqtgraph/taurustrendset.py
taurus_pyqtgraph/titlepatterneditor.py
taurus_pyqtgraph/trend.py
taurus_pyqtgraph/util.py
taurus_pyqtgraph/y2axis.py
taurus_pyqtgraph/examples/__init__.py
taurus_pyqtgraph/examples/axislabels.py
taurus_pyqtgraph/examples/legendExample.py
taurus_pyqtgraph/examples/taurusplotdataitem.py
taurus_pyqtgraph/examples/taurustrendset.py
taurus_pyqtgraph/examples/y2axis.py
taurus_pyqtgraph/ui/CurvesAppearanceChooser.ui
taurus_pyqtgraph/ui/TaurusItemConfDlg.ui
taurus_pyqtgraph-0.9.7.dist-info/LICENSE.txt
taurus_pyqtgraph-0.9.7.dist-info/METADATA
taurus_pyqtgraph-0.9.7.dist-info/WHEEL
taurus_pyqtgraph-0.9.7.dist-info/entry_points.txt
taurus_pyqtgraph-0.9.7.dist-info/top_level.txt
taurus_pyqtgraph-0.9.7.dist-info/RECORD
