Metadata-Version: 2.1
Name: taurus-pyqtgraph
Version: 0.9.7
Summary: Taurus extension providing pyqtgraph-based widgets
Home-page: https://gitlab.com/taurus-org/taurus_pyqtgraph
Author: Taurus Community
Maintainer: Taurus Community
Maintainer-email: tauruslib-devel@lists.sourceforge.net
License: LGPLv3+
Download-URL: https://gitlab.com/taurus-org/taurus_pyqtgraph
Keywords: Taurus,pyqtgraph,plugin,widgets
Platform: Linux
Platform: Windows
Classifier: Development Status :: 3 - Alpha
Classifier: Environment :: X11 Applications :: Qt
Classifier: Environment :: Win32 (MS Windows)
Classifier: Intended Audience :: Developers
Classifier: Intended Audience :: Science/Research
Classifier: License :: OSI Approved :: GNU Lesser General Public License v3 or later (LGPLv3+)
Classifier: Operating System :: Microsoft :: Windows
Classifier: Operating System :: POSIX
Classifier: Operating System :: POSIX :: Linux
Classifier: Operating System :: Unix
Classifier: Operating System :: OS Independent
Classifier: Natural Language :: English
Classifier: Programming Language :: Python :: 3
Classifier: Programming Language :: Python :: 3.5
Classifier: Programming Language :: Python :: 3.6
Classifier: Programming Language :: Python :: 3.7
Classifier: Programming Language :: Python :: 3.8
Classifier: Programming Language :: Python :: 3.9
Classifier: Topic :: Scientific/Engineering
Classifier: Topic :: Software Development :: Libraries
Classifier: Topic :: Software Development :: User Interfaces
Classifier: Topic :: Software Development :: Widget Sets
Requires-Python: >=3.5
License-File: LICENSE.txt
Requires-Dist: pyqtgraph>=0.11
Requires-Dist: click
Requires-Dist: taurus>=4.5.2
Requires-Dist: lxml
Requires-Dist: ply
Provides-Extra: archiving
Requires-Dist: pyhdbpp; extra == "archiving"
